{
    "342": 1,
    "390": 1,
    "478": 1,
    "492": 1,
    "494": 1,
    "509": 1,
    "526": 1,
    "543": 1,
    "560": 1,
    "566": 1,
    "593": 1,
    "610": 1,
    "627": 1,
    "629": 1,
    "635": 1,
    "644": 1,
    "664": 2,
    "665": 1,
    "666": 1,
    "670": 1,
    "678": 1,
    "685": 1,
    "690": 1,
    "706": 1,
    "720": 1,
    "723": 1,
    "732": 1,
    "733": 1,
    "743": 1,
    "750": 1,
    "754": 1,
    "756": 1,
    "762": 2,
    "766": 1,
    "770": 1,
    "783": 1,
    "787": 1,
    "789": 1,
    "799": 2,
    "818": 1,
    "830": 1,
    "836": 1,
    "850": 1,
    "851": 1,
    "856": 1,
    "863": 2,
    "865": 1,
    "872": 1,
    "873": 1,
    "883": 1,
    "899": 1,
    "914": 2,
    "923": 1,
    "924": 1,
    "931": 2,
    "965": 1,
    "991": 1,
    "995": 1,
    "996": 1,
    "1020": 1,
    "1021": 1,
    "1026": 1,
    "1028": 1,
    "1044": 1,
    "1045": 1,
    "1064": 1,
    "1084": 1,
    "1087": 1,
    "1093": 1,
    "1104": 1,
    "1108": 1,
    "1128": 1,
    "1130": 1,
    "1132": 1,
    "1150": 1,
    "1174": 1,
    "1178": 1,
    "1213": 1,
    "1215": 1,
    "1217": 1,
    "1222": 1,
    "1248": 1,
    "1260": 1,
    "1264": 1,
    "1265": 1,
    "1293": 1,
    "1298": 1,
    "1318": 1,
    "1343": 1,
    "1381": 1,
    "1416": 1,
    "1454": 1,
    "1496": 1,
    "6000": 1,
    "num_particles": 100,
    "sweep_per_turn": 1.0
}